fediblockhole/__init__.py
fediblockhole/blocklists.py
fediblockhole/const.py
fediblockhole-0.4.6.dist-info/METADATA
fediblockhole-0.4.6.dist-info/WHEEL
fediblockhole-0.4.6.dist-info/entry_points.txt
fediblockhole-0.4.6.dist-info/licenses/LICENSE
fediblockhole-0.4.6.dist-info/RECORD
