Metadata-Version: 2.3
Name: fediblockhole
Version: 0.4.6
Summary: Federated blocklist management for Mastodon
Project-URL: homepage, https://github.com/eigenmagic/fediblockhole
Project-URL: documentation, https://github.com/eigenmagic/fediblockhole
Project-URL: repository, https://github.com/eigenmagic/fediblockhole
Author: Justin Warren
Author-email: justin@eigenmagic.com
License:                     GNU AFFERO GENERAL PUBLIC LICENSE
License-File: LICENSE
Keywords: fediblock,mastodon
Classifier: Development Status :: 4 - Beta
Classifier: Intended Audience :: Developers
Classifier: Intended Audience :: System Administrators
Classifier: License :: OSI Approved :: GNU Affero General Public License v3
Classifier: Natural Language :: English
Classifier: Programming Language :: Python :: 3
Classifier: Programming Language :: Python :: 3.6
Classifier: Programming Language :: Python :: 3.7
Classifier: Programming Language :: Python :: 3.8
Classifier: Programming Language :: Python :: 3.9
Classifier: Programming Language :: Python :: 3.10
Requires-Python: >=3.6
Requires-Dist: requests
Requires-Dist: toml
